[
  {
    "especializacao": "Financeiro",
    "id": "7edbd27a-ae25-46fa-b5fe-c782ee4396bf",
    "nome": "João Consultor",
    "email": "joao@consult.com"
  },
  {
    "especializacao": "Financeiro",
    "id": "60182c1b-b4ef-4799-b96f-2094730c76da",
    "nome": "João Consultor",
    "email": "joao@consult.com"
  },
  {
    "especializacao": "Financeiro",
    "id": "508fe5f6-cfd1-46aa-9be5-b8a39d2e18d0",
    "nome": "João Consultor",
    "email": "joao@consult.com"
  },
  {
    "especializacao": "Financeiro",
    "id": "5bbf9189-c277-4dbe-be55-b21508bb24bc",
    "nome": "João Consultor",
    "email": "joao@consult.com"
  },
  {
    "especializacao": "Financeiro",
    "id": "c31f0751-1e1c-4e6a-ab48-47e4baa870b5",
    "nome": "João Consultor",
    "email": "joao@consult.com"
  },
  {
    "especializacao": "Financeiro",
    "id": "2b5eb4d0-f047-4afb-a412-8215768cd152",
    "nome": "João Consultor",
    "email": "joao@consult.com"
  },
  {
    "especializacao": "Financeiro",
    "id": "8db8e38f-dc41-4014-a2dc-5e6414f755aa",
    "nome": "João Consultor",
    "email": "joao@consult.com"
  },
  {
    "especializacao": "Financeiro",
    "id": "ebc37dac-3930-443f-9851-626b840ad6df",
    "nome": "João Consultor",
    "email": "joao@consult.com"
  },
  {
    "especializacao": "Financeiro",
    "id": "5f15c52d-4cf6-4bb9-b226-cd1637c5f882",
    "nome": "João Consultor",
    "email": "joao@consult.com"
  },
  {
    "especializacao": "Financeiro",
    "id": "19a78cfc-ce78-42aa-8f17-7a86fb12232f",
    "nome": "João Consultor",
    "email": "joao@consult.com"
  },
  {
    "especializacao": "Financeiro",
    "id": "9cf356c2-1a0f-45a0-96e9-3f92c3e00b17",
    "nome": "João Consultor",
    "email": "joao@consult.com"
  }
]